__init__.py
command_describer.py
configuration_handler.py
create_file.py
delete_file.py
edit_file_with_emacs.py
environment_handler.py
file_handler.py
file_lister.py
git_handler.py
kazuki.py
version_handler.py
kazuki_help-0.0.2.dist-info/LICENSE
kazuki_help-0.0.2.dist-info/METADATA
kazuki_help-0.0.2.dist-info/WHEEL
kazuki_help-0.0.2.dist-info/entry_points.txt
kazuki_help-0.0.2.dist-info/top_level.txt
kazuki_help-0.0.2.dist-info/RECORD
