Metadata-Version: 2.1
Name: kazuki_help
Version: 0.0.2
Summary: kazuki_help
Author-email: Kazuki Tsujimoto <fpd69555@kwansei.ac.jp>
Project-URL: Homepage, https://github.com/pypa/sampleproject
Project-URL: Issues, https://github.com/pypa/sampleproject/issues
Classifier: Programming Language :: Python :: 3
Classifier: License :: OSI Approved :: MIT License
Classifier: Operating System :: OS Independent
Requires-Python: >=3.8
License-File: LICENSE
